Metadata-Version: 2.1
Name: gradientmodel
Version: 0.0.2
Summary: Calculate the surface impedance of a rough metal surface using the Gradient Model (GM)
Home-page: https://github.com/garrettj403/GradientModel/
Author: John Garrett
Author-email: garrettj403@gmail.com
License: MIT
Project-URL: Changelog, https://github.com/garrettj403/GradientModel/blob/master/CHANGES.md
Project-URL: Issue Tracker, https://github.com/garrettj403/GradientModel/issues
Platform: any
Classifier: Intended Audience :: Science/Research
Classifier: License :: OSI Approved :: MIT License
Classifier: Natural Language :: English
Classifier: Programming Language :: Python :: 3.5
Classifier: Programming Language :: Python :: 3.6
Classifier: Programming Language :: Python :: 3.7
Provides-Extra: examples
License-File: LICENSE.md
